loxone_api/__init__.py
loxone_api/auth.py
loxone_api/cli.py
loxone_api/client.py
loxone_api/const.py
loxone_api/models.py
loxone_api-0.1.25.dist-info/METADATA
loxone_api-0.1.25.dist-info/WHEEL
loxone_api-0.1.25.dist-info/entry_points.txt
loxone_api-0.1.25.dist-info/top_level.txt
loxone_api-0.1.25.dist-info/RECORD
