Metadata-Version: 2.4
Name: loxone-api
Version: 0.1.25
Summary: Async client for the Loxone Miniserver
Author: Tim
Requires-Dist: aiohttp
